pyencourage/__init__.py
pyencourage/encourage_en.py
pyencourage/pyencourage.py
pyencouragecli/__init__.py
pyencouragecli/pyencourage.py
pyencouragecli/pyencouragement.py
pyencourage-0.1.4.dist-info/LICENCE.txt
pyencourage-0.1.4.dist-info/METADATA
pyencourage-0.1.4.dist-info/WHEEL
pyencourage-0.1.4.dist-info/entry_points.txt
pyencourage-0.1.4.dist-info/top_level.txt
pyencourage-0.1.4.dist-info/RECORD
