Metadata-Version: 2.1
Name: pyencourage
Version: 0.1.4
Summary: One line encouragement for programmers (encouragement as a service)
Home-page: https://github.com/seantibor/pyencourage
Author: Sean Tibor
Author-email: sean.tibor@gmail.com
License: BSD License
Keywords: pyencourage,pyencouragement,encouragement,encourage
Platform: ALL
Classifier: Development Status :: 4 - Beta
Classifier: Topic :: Utilities
Classifier: License :: OSI Approved :: BSD License
Classifier: Programming Language :: Python :: 2
Classifier: Programming Language :: Python :: 3
Provides-Extra: doc
Requires-Dist: mkdocs ; extra == 'doc'
Provides-Extra: test
Requires-Dist: pytest ; extra == 'test'
Requires-Dist: coverage ; extra == 'test'
Requires-Dist: tox ; extra == 'test'
